devpackage/__init__.py
devpackage/cli.py
devpackage/path.py
devpackage/version.py
devpackage-0.3.dist-info/LICENSE
devpackage-0.3.dist-info/METADATA
devpackage-0.3.dist-info/WHEEL
devpackage-0.3.dist-info/entry_points.txt
devpackage-0.3.dist-info/top_level.txt
devpackage-0.3.dist-info/RECORD
