Metadata-Version: 2.1
Name: devpackage
Version: 0.3
Summary: UNKNOWN
Home-page: https://github.com/Xython/devpackage
Author: Xython
Author-email: twshere@outlook.com
License: mit
Keywords: developing tools,package development
Platform: any
Classifier: Programming Language :: Python :: 3.6
Classifier: Programming Language :: Python :: 3.7
Classifier: Programming Language :: Python :: Implementation :: CPython
Requires-Python: >=3.6.0
Requires-Dist: argser
Requires-Dist: lice
